pycounts_thomassiu/__init__.py
pycounts_thomassiu/plotting.py
pycounts_thomassiu/pycounts.py
pycounts_thomassiu-2.1.0.dist-info/LICENSE
pycounts_thomassiu-2.1.0.dist-info/WHEEL
pycounts_thomassiu-2.1.0.dist-info/METADATA
pycounts_thomassiu-2.1.0.dist-info/RECORD
